voprov/__init__.py
voprov/models/__init__.py
voprov/models/constants.py
voprov/models/model.py
voprov/models/voprovConfigurations.py
voprov/models/voprovDescriptions.py
voprov/models/voprovRelations.py
voprov/serializers/__init__.py
voprov/serializers/provjson.py
voprov/serializers/provn.py
voprov/serializers/voyaml.py
voprov/serializers/xml.py
voprov/visualization/__init__.py
voprov/visualization/dot.py
voprov/visualization/graph.py
voprov/visualization/plotly.py
voprov-0.0.4.dist-info/AUTHORS.rst
voprov-0.0.4.dist-info/LICENSE
voprov-0.0.4.dist-info/METADATA
voprov-0.0.4.dist-info/WHEEL
voprov-0.0.4.dist-info/top_level.txt
voprov-0.0.4.dist-info/RECORD
