Metadata-Version: 2.1
Name: voprov
Version: 0.0.4
Summary: A library for IVOA Provenance Data Model supporting PROV-JSON, PROV-XML and PROV-N
Home-page: https://github.com/sanguillon/voprov/
Author: Benjamin Parciany
Author-email: benjamin.parciany@obspm.fr
License: MIT
Keywords: provenance,graph,model,VOPROV,provenance-dm,PROVENANCE-DM,PROV-JSON,JSON,PROV-XML,PROV-N
Classifier: Development Status :: 4 - Beta
Classifier: Intended Audience :: Developers
Classifier: Intended Audience :: Information Technology
Classifier: Intended Audience :: Science/Research
Classifier: License :: OSI Approved :: MIT License
Classifier: Natural Language :: French
Classifier: Operating System :: OS Independent
Classifier: Programming Language :: Python :: 3
Classifier: Programming Language :: Python :: 3.5
Classifier: Programming Language :: Python :: 3.6
Classifier: Programming Language :: Python :: 3.7
Classifier: Programming Language :: Python :: 3.8
Classifier: Programming Language :: Python :: 3.11
Classifier: Topic :: Scientific/Engineering :: Information Analysis
Requires-Python: >=3
License-File: LICENSE
License-File: AUTHORS.rst
Requires-Dist: prov (>=2.0)
Provides-Extra: dot
Requires-Dist: pydot (>=1.2.0) ; extra == 'dot'
